README.rst
setup.py
picotui/__init__.py
picotui/basewidget.py
picotui/context.py
picotui/defs.py
picotui/dialogs.py
picotui/editor.py
picotui/editorext.py
picotui/menu.py
picotui/posixread.py
picotui/read_test.py
picotui/read_test_no_poll.py
picotui/readinput.py
picotui/screen.py
picotui/widgets.py
picotui.egg-info/PKG-INFO
picotui.egg-info/SOURCES.txt
picotui.egg-info/dependency_links.txt
picotui.egg-info/top_level.txt