Metadata-Version: 1.0
Name: picotui
Version: 1.2
Summary: A simple text user interface (TUI) library.
Home-page: https://github.com/pfalcon/picotui
Author: Paul Sokolovsky
Author-email: pfalcon@users.sourceforge.net
License: MIT
Platform: UNKNOWN
